{"1027": {"A2KUWEN5J9VHLM": {"assignment_id": "32EYX73OY09BN4GTKRA184BUHR3RU1", "feedback": ["Please enter your feedback here"]}, "A20TZ24SQJ8B9T": {"assignment_id": "3A4TN5196KI2CGLQ2VD70UNINIYHCK", "feedback": ["Please enter your feedback here"]}, "AVHZJ2HQJG3NB": {"assignment_id": "3KV0LJBBH2LSAWBKBPJFHUU0454MR8", "feedback": ["Please enter your feedback here"]}, "A1OMWAZ59NKDKD": {"assignment_id": "33SA9F9TRXUZ640TTL52RLX8NIOEWA", "feedback": ["Please enter your feedback here"]}, "A1SDJOMBXA43VR": {"assignment_id": "3NS0A6KXC481KD1PA3FXQSC2H07GZJ", "feedback": ["Please enter your feedback here"]}}, "1030": {"A30BM2XZJR61S1": {"assignment_id": "3WMINLGALB3N2TDCWP3FJ80EAN8AC2", "feedback": ["Please enter your feedback here"]}, "A1NOINYD1FZ55T": {"assignment_id": "30X31N5D63Q39A28TBTFYD4WWQXSAH", "feedback": ["nice work."]}, "A1SDJOMBXA43VR": {"assignment_id": "3018Q3ZVOIQR8V2VEMTA83Z0AOBRAP", "feedback": ["Please enter your feedback here"]}, "A27TLMSTDJ4UN4": {"assignment_id": "3VHHR074H3HYMV9K2ZKUC0OB3OFL71", "feedback": ["Please enter your feedback here"]}}, "1034": {"A30BM2XZJR61S1": {"assignment_id": "3YW4XOSQKQLNUZHCMXVM2DTHDT9U18", "feedback": ["Please enter your feedback here"]}, "A1NOINYD1FZ55T": {"assignment_id": "3OWEPKL089COAVC5EC09PSS08JJ7NT", "feedback": ["nice work."]}, "A1SDJOMBXA43VR": {"assignment_id": "3L0KT67Y8EG45S0B9H7V1ZM3ZHXSYO", "feedback": ["Please enter your feedback here"]}}, "1035": {"A1SDJOMBXA43VR": {"assignment_id": "358UUM7WRZ39PT4X7JHQYCXA9G5R7Y", "feedback": ["Please enter your feedback here"]}, "A1NOINYD1FZ55T": {"assignment_id": "3GNCZX450IN6WIMG1UPL38ZL96RAPK", "feedback": ["nice work."]}, "A3RKC05CTZRX2M": {"assignment_id": "3Y9N9SS8LYBXN0K5N6JGG64QPDSD39", "feedback": ["Please enter your feedback here"]}}, "89": {"ARCROXZI0H0SW": {"assignment_id": "3RUIQRXJBBOX1GYM6TL4V56CZL2LLJ", "feedback": [null]}, "A2DHLFPCDUTK2O": {"assignment_id": "3AMYWKA6YBMNOGYCWHVUY3S94VJO6W", "feedback": [null]}, "A5BCSSPC180AG": {"assignment_id": "3OJSZ2ATDSWKK66ZAC4NVBSEIB675H", "feedback": ["It is not possible to determine without further context whether the final example qualifies as an objection but this seems the most likely answer"]}}, "285": {"A1Q1HSGBD1POWV": {"assignment_id": "3JPSL1DZ5SZ6TXA3LFCTZJUQA43NA5", "feedback": [null]}, "A3GDG4D8N1M220": {"assignment_id": "3L4PIM1GQTGS4D0YUS7QBPH7ESWRY8", "feedback": [null]}, "AD1ILDUXZHASF": {"assignment_id": "3NXNZ5RS1AX3LT8BD2H47RXG47P798", "feedback": [null]}}, "529": {"ARCROXZI0H0SW": {"assignment_id": "3ERET4BTVM9RG8FVWW6DBW22ARHK9J", "feedback": [null]}, "A1RATFICCKLCQ": {"assignment_id": "33LK57MYLT54AIAG539EF6V56OJZSV", "feedback": [null]}, "A2DHLFPCDUTK2O": {"assignment_id": "3RXCAC0YIRPM0H021DFKD8FYJ4JG8O", "feedback": [null]}}}